Angad_PES/DDCO/fulladder.v
module andgate (y,a,b);
	input a,b;
	output y;
	assign y = a&b; 
endmodule

module notgate (y,a);
	input a;
	output y;
	assign y = !a; 
endmodule

module xorgate (y,a,b);
	input a,b;
	output y;
	assign y = a^b; 
endmodule

module orgate (y,a,b);
	input a,b;
	output y;
	assign y = a|b; 
endmodule

module fulladder(x,y,z,s,c);
	output s,c;
	input x,y,z;
	wire w1, w2, w3;
	xorgate g1 (w1, x, y);
	xorgate g2 (s, w1, z);
	andgate g3 (w2, w1, z);
	andgate g4 (w3, x, y);
	orgate g5 (c, w3, w2);
endmodule

Angad_PES/DDCO/fulladder_tb.v
module fulladder_test;
	reg x, y, z;  
	wire s, c;    
	fulladder fulladder_test(x,y,z,s,c);
	
	initial  
begin   
    #0 x=0; y=0; z=0;
    #100 x=0; y=0; z=1;
    #100 x=0; y=1; z=0;
    #100 x=0; y=1; z=1;
    #100 x=1; y=0; z=0;
    #100 x=1; y=0; z=1;
    #100 x=1; y=1; z=0;
    #100 x=1; y=1; z=1;
end   

initial
begin
    $monitor($time, " x=%b, y=%b, z=%b, s=%b, c=%b", x, y, z, s, c); 
	end
	initial
	begin
	$dumpfile("fulladder_test.vcd");
		$dumpvars(0, fulladder_test);
	end
endmodule

Angad_PES/DDCO/fulladder_test.vcd
$date
	Sun Oct  6 23:02:56 2024
$end
$version
	Icarus Verilog
$end
$timescale
	1s
$end
$scope module fulladder_test $end
$scope module fulladder_test $end
$var wire 1 ! x $end
$var wire 1 " y $end
$var wire 1 # z $end
$var wire 1 $ w3 $end
$var wire 1 % w2 $end
$var wire 1 & w1 $end
$var wire 1 ' s $end
$var wire 1 ( c $end
$scope module g1 $end
$var wire 1 ! a $end
$var wire 1 " b $end
$var wire 1 & y $end
$upscope $end
$scope module g2 $end
$var wire 1 & a $end
$var wire 1 # b $end
$var wire 1 ' y $end
$upscope $end
$scope module g3 $end
$var wire 1 & a $end
$var wire 1 # b $end
$var wire 1 % y $end
$upscope $end
$scope module g4 $end
$var wire 1 ! a $end
$var wire 1 " b $end
$var wire 1 $ y $end
$upscope $end
$scope module g5 $end
$var wire 1 $ a $end
$var wire 1 % b $end
$var wire 1 ( y $end
$upscope $end
$upscope $end
$upscope $end
$enddefinitions $end
#0
$dumpvars
0(
0'
0&
0%
0$
0#
0"
0!
$end
#100
1'
1#
#200
1&
0#
1"
#300
1(
0'
1%
1#
#400
0(
1'
0%
0#
0"
1!
#500
1(
0'
1%
1#
#600
0%
0&
1$
0#
1"
#700
1'
1#
