Hemanth_PES/DDCO/alu.v
module alu (input wire [1:0] op, input wire [15:0] i0, i1, output reg [15:0] o, output wire cout);
    
      // Declare wires here
      wire [15:0] sum;
      wire [15:0] diff;
      wire [15:0] logic_and;
      wire [15:0] logic_or;
      reg carry;
      reg overflow;

  // Instantiate modules here
  assign sum = i0 + i1;
  assign diff = i0 - i1;
  assign logic_and = i0 & i1;
  assign logic_or = i0 | i1;

  always @(*) begin
    case (op)
      2'b00: begin
        o = sum;
        carry = sum[15];
        overflow = (i0[15] == i1[15] && sum[15] != i0[15]);
      end
      2'b01: begin
        o = diff;
        carry = diff[15];
        overflow = (i0[15] != i1[15] && diff[15] != i0[15]);
      end
      2'b10: begin
        o = logic_and;
        carry = 1'b0;
        overflow = 1'b0;
      end
      2'b11: begin
        o = logic_or;
        carry = 1'b0;
        overflow = 1'b0;
      end
    endcase
  end

endmodule

Angad_PES/DDCO/tb_alu.v
`timescale 1 ns / 100 ps
`define TESTVECS 16

module tb;
  reg clk, reset;
  reg [1:0] op; reg [15:0] i0, i1;
  wire [15:0] o; wire cout;
  reg [33:0] test_vecs [0:(`TESTVECS-1)];
  integer i;
  initial begin $dumpfile("tb_alu.vcd"); $dumpvars(0,tb); end
  initial begin reset = 1'b1; #12.5 reset = 1'b0; end
  initial clk = 1'b0; always #5 clk =~ clk;
  initial begin
    $monitor("op=%b, i0=%h, i1=%h, o=%h, cout=%b", op, i0, i1, o, cout);
    test_vecs[0][33:32] = 2'b00; test_vecs[0][31:16] = 16'h0000;test_vecs[0][15:0] = 16'h0000;
    test_vecs[1][33:32] = 2'b00; test_vecs[1][31:16] = 16'haa55;test_vecs[1][15:0] = 16'h55aa;
    test_vecs[2][33:32] = 2'b00; test_vecs[2][31:16] = 16'hffff;test_vecs[2][15:0] = 16'h0001;
    test_vecs[3][33:32] = 2'b00; test_vecs[3][31:16] = 16'h0001;test_vecs[3][15:0] = 16'h7fff;
    test_vecs[4][33:32] = 2'b01; test_vecs[4][31:16] = 16'h0000;test_vecs[4][15:0] = 16'h0000;
    test_vecs[5][33:32] = 2'b01; test_vecs[5][31:16] = 16'haa55;test_vecs[5][15:0] = 16'h55aa;
    test_vecs[6][33:32] = 2'b01; test_vecs[6][31:16] = 16'hffff;test_vecs[6][15:0] = 16'h0001;
    test_vecs[7][33:32] = 2'b01; test_vecs[7][31:16] = 16'h0001;test_vecs[7][15:0] = 16'h7fff;
    test_vecs[8][33:32] = 2'b10; test_vecs[8][31:16] = 16'h0000;test_vecs[8][15:0] = 16'h0000;
    test_vecs[9][33:32] = 2'b10; test_vecs[9][31:16] = 16'haa55;test_vecs[9][15:0] = 16'h55aa;
    test_vecs[10][33:32] = 2'b10; test_vecs[10][31:16] = 16'hffff;test_vecs[10][15:0] = 16'h0001;
    test_vecs[11][33:32] = 2'b10; test_vecs[11][31:16] = 16'h0001;test_vecs[11][15:0] = 16'h7fff;
    test_vecs[12][33:32] = 2'b11; test_vecs[12][31:16] = 16'h0000;test_vecs[12][15:0] = 16'h0000;
    test_vecs[13][33:32] = 2'b11; test_vecs[13][31:16] = 16'haa55;test_vecs[13][15:0] = 16'h55aa;
    test_vecs[14][33:32] = 2'b11; test_vecs[14][31:16] = 16'hffff;test_vecs[14][15:0] = 16'h0001;
    test_vecs[15][33:32] = 2'b11; test_vecs[15][31:16] = 16'h0001;test_vecs[15][15:0] = 16'h7fff;
  end
  initial {op, i0, i1} = 0;
  alu alu_0 (op, i0, i1, o, cout);
  initial begin
    #6 for(i=0;i<`TESTVECS;i=i+1)
      begin #10 {op, i0, i1}=test_vecs[i]; end
    #100 $finish;
  end
endmodule

Hemanth_PES/DDCO/tb_alu.vcd
$date
	Tue Sep  3 15:22:46 2024
$end
$version
	Icarus Verilog
$end
$timescale
	100ps
$end
$scope module tb $end
$var wire 1 ! cout $end
$var wire 16 " o [15:0] $end
$var reg 1 # clk $end
$var reg 16 $ i0 [15:0] $end
$var reg 16 % i1 [15:0] $end
$var reg 2 & op [1:0] $end
$var reg 1 ' reset $end
$var integer 32 ( i [31:0] $end
$scope module alu_0 $end
$var wire 1 ! cout $end
$var wire 16 ) i0 [15:0] $end
$var wire 16 * i1 [15:0] $end
$var wire 16 + logic_and [15:0] $end
$var wire 16 , logic_or [15:0] $end
$var wire 2 - op [1:0] $end
$var wire 16 . sum [15:0] $end
$var wire 16 / diff [15:0] $end
$var reg 1 0 carry $end
$var reg 16 1 o [15:0] $end
$var reg 1 2 overflow $end
$upscope $end
$upscope $end
$enddefinitions $end
$comment Show the parameter values. $end
$dumpall
$end
#0
$dumpvars
02
b0 1
00
b0 /
b0 .
b0 -
b0 ,
b0 +
b0 *
b0 )
bx (
1'
b0 &
b0 %
b0 $
0#
b0 "
z!
$end
#50
1#
#60
b0 (
#100
0#
#125
0'
#150
1#
#160
b1 (
#200
0#
#250
1#
#260
b1111111111111111 ,
10
b1111111111111111 "
b1111111111111111 1
b10 (
b1010101001010101 $
b1010101001010101 )
b1111111111111111 .
b101010010101011 /
b101010110101010 %
b101010110101010 *
#300
0#
#350
1#
#360
b1 +
00
b0 "
b0 1
b11 (
b1111111111111111 $
b1111111111111111 )
b0 .
b1111111111111110 /
b1 %
b1 *
#400
0#
#450
1#
#460
b111111111111111 ,
12
10
b1000000000000000 "
b1000000000000000 1
b100 (
b1 $
b1 )
b1000000000000000 .
b1000000000000010 /
b111111111111111 %
b111111111111111 *
#500
0#
#550
1#
#560
b0 +
b0 ,
02
00
b0 "
b0 1
b101 (
b1 &
b1 -
b0 $
b0 )
b0 .
b0 /
b0 %
b0 *
#600
0#
#650
1#
#660
b1111111111111111 ,
12
b101010010101011 "
b101010010101011 1
b110 (
b1010101001010101 $
b1010101001010101 )
b1111111111111111 .
b101010010101011 /
b101010110101010 %
b101010110101010 *
#700
0#
#750
1#
#760
b1 +
02
10
b1111111111111110 "
b1111111111111110 1
b111 (
b1111111111111111 $
b1111111111111111 )
b0 .
b1111111111111110 /
b1 %
b1 *
#800
0#
#850
1#
#860
b111111111111111 ,
b1000000000000010 "
b1000000000000010 1
b1000 (
b1 $
b1 )
b1000000000000000 .
b1000000000000010 /
b111111111111111 %
b111111111111111 *
#900
0#
#950
1#
#960
b0 +
b0 ,
00
b0 "
b0 1
b1001 (
b10 &
b10 -
b0 $
b0 )
b0 .
b0 /
b0 %
b0 *
#1000
0#
#1050
1#
#1060
b1111111111111111 ,
b1010 (
b1010101001010101 $
b1010101001010101 )
b1111111111111111 .
b101010010101011 /
b101010110101010 %
b101010110101010 *
#1100
0#
#1150
1#
#1160
b1 "
b1 1
b1 +
b1011 (
b1111111111111111 $
b1111111111111111 )
b0 .
b1111111111111110 /
b1 %
b1 *
#1200
0#
#1250
1#
#1260
b111111111111111 ,
b1100 (
b1 $
b1 )
b1000000000000000 .
b1000000000000010 /
b111111111111111 %
b111111111111111 *
#1300
0#
#1350
1#
#1360
b0 +
b0 ,
b0 "
b0 1
b1101 (
b11 &
b11 -
b0 $
b0 )
b0 .
b0 /
b0 %
b0 *
#1400
0#
#1450
1#
#1460
b1111111111111111 "
b1111111111111111 1
b1111111111111111 ,
b1110 (
b1010101001010101 $
b1010101001010101 )
b1111111111111111 .
b101010010101011 /
b101010110101010 %
b101010110101010 *
#1500
0#
#1550
1#
#1560
b1 +
b1111 (
b1111111111111111 $
b1111111111111111 )
b0 .
b1111111111111110 /
b1 %
b1 *
#1600
0#
#1650
1#
#1660
b111111111111111 "
b111111111111111 1
b111111111111111 ,
b10000 (
b1 $
b1 )
b1000000000000000 .
b1000000000000010 /
b111111111111111 %
b111111111111111 *
